LICENCE.txt
MANIFEST.in
README.md
setup.py
version.py
extern/__init__.py
extern/multi_runner.py
extern.egg-info/PKG-INFO
extern.egg-info/SOURCES.txt
extern.egg-info/dependency_links.txt
extern.egg-info/top_level.txt
test/test_extern.py