Metadata-Version: 2.1
Name: extern
Version: 0.4.1
Summary: Opinionated version of Python's subprocess
Home-page: UNKNOWN
Author: Ben Woodcroft
Author-email: donttrustben@gmail.com
License: MIT
Platform: UNKNOWN
